intercambio/__init__.py
intercambio/itc.py
intercambio-0.1.0.dist-info/METADATA
intercambio-0.1.0.dist-info/WHEEL
intercambio-0.1.0.dist-info/top_level.txt
intercambio-0.1.0.dist-info/RECORD
